[{"primary-type": "Album", "artist-credit": [{"artist": {"disambiguation": "Canadian actor/rapper", "name": "Drake", "sort-name": "Drake", "id": "9fff2f8a-21e6-47de-a2b8-7f449929d43f"}}], "ext:score": "100", "id": "8b4b176b-3ecc-4905-abfe-f6f00538df62", "title": "The Drizzy Effect", "artist-credit-phrase": "Drake", "release-list": [{"title": "The Drizzy Effect", "status": "Bootleg", "id": "7224af10-75f2-41df-8470-11bff963177a"}], "secondary-type-list": ["Mixtape/Street"], "type": "Album", "release-count": 1}, {"primary-type": "Single", "artist-credit": [{"artist": {"disambiguation": "Canadian actor/rapper", "name": "Drake", "sort-name": "Drake", "id": "9fff2f8a-21e6-47de-a2b8-7f449929d43f"}}], "ext:score": "100", "id": "14aaf0a8-b9b0-42d0-b15f-9f17b90c4ea5", "title": "Started From the Bottom", "artist-credit-phrase": "Drake", "release-list": [{"title": "Started From the Bottom", "status": "Official", "id": "cfd17ccb-a45d-43b6-bfca-4cc8aa3da8fb"}, {"title": "Started From the Bottom", "status": "Official", "id": "95383a62-a9a6-4ba0-b925-e140db84b788"}], "type": "Single", "release-count": 2}, {"primary-type": "Single", "artist-credit": [{"artist": {"disambiguation": "Canadian actor/rapper", "name": "Drake", "sort-name": "Drake", "id": "9fff2f8a-21e6-47de-a2b8-7f449929d43f"}}], "ext:score": "100", "id": "4a8e2445-11b9-4c29-a186-24ba70bbab1a", "title": "Trust Issues", "artist-credit-phrase": "Drake", "release-list": [{"title": "Trust Issues", "status": "Official", "id": "aaa383da-f978-4aa0-a8fd-a386c5976922"}, {"title": "Trust Issues", "status": "Official", "id": "2afcc5b8-2663-4efc-b3d4-f2a9baf0a278"}], "type": "Single", "release-count": 2}, {"primary-type": "Single", "artist-credit": [{"artist": {"disambiguation": "Canadian actor/rapper", "name": "Drake", "sort-name": "Drake", "id": "9fff2f8a-21e6-47de-a2b8-7f449929d43f"}}], "ext:score": "100", "id": "71b23f03-ee2f-4d7e-ac69-db0a24b0a883", "title": "I'm Ready for You", "artist-credit-phrase": "Drake", "release-list": [{"title": "I'm Ready for You", "status": "Official", "id": "4b2cf22d-6c6c-4caf-b514-d718747905f3"}], "type": "Single", "release-count": 1}, {"primary-type": "Single", "artist-credit": [{"artist": {"disambiguation": "Canadian actor/rapper", "name": "Drake", "sort-name": "Drake", "id": "9fff2f8a-21e6-47de-a2b8-7f449929d43f"}}], "ext:score": "100", "id": "d5e449a2-4fd7-4634-9cc9-35c2a8066a90", "title": "Club Paradise", "artist-credit-phrase": "Drake", "release-list": [{"title": "Club Paradise", "status": "Official", "id": "3bba7bfe-4596-4085-8ff9-7c98677151b9"}], "type": "Single", "release-count": 1}, {"primary-type": "Album", "artist-credit": [{"artist": {"disambiguation": "Canadian actor/rapper", "name": "Drake", "sort-name": "Drake", "id": "9fff2f8a-21e6-47de-a2b8-7f449929d43f"}}], "ext:score": "100", "id": "c1ab705e-d90e-4d13-af47-2a4aa2409bad", "title": "Heartbreak Drake 3 (The First Semester)", "artist-credit-phrase": "Drake", "release-list": [{"title": "Heartbreak Drake 3 (The First Semester)", "status": "Bootleg", "id": "7260bf0b-c088-44c8-a49b-3ace22dafc60"}], "secondary-type-list": ["Mixtape/Street"], "type": "Album", "release-count": 1}, {"primary-type": "Album", "artist-credit": [{"artist": {"disambiguation": "Canadian actor/rapper", "name": "Drake", "sort-name": "Drake", "id": "9fff2f8a-21e6-47de-a2b8-7f449929d43f"}}], "ext:score": "100", "id": "186db56c-f506-498d-951e-a20b99528d7e", "title": "Made in October", "artist-credit-phrase": "Drake", "release-list": [{"title": "Made in October", "status": "Promotion", "id": "7ca40da7-3cbf-414f-be79-fff1ac74fe17"}], "secondary-type-list": ["Mixtape/Street"], "type": "Album", "release-count": 1}, {"primary-type": "Single", "artist-credit": [{"artist": {"disambiguation": "Canadian actor/rapper", "name": "Drake", "sort-name": "Drake", "id": "9fff2f8a-21e6-47de-a2b8-7f449929d43f"}}], "ext:score": "100", "tag-list": [{"name": "hip hop", "count": "1"}], "id": "5744e211-129b-44ba-bbf0-634c4ccfa4ab", "title": "Best I Ever Had", "artist-credit-phrase": "Drake", "release-count": 1, "type": "Single", "release-list": [{"title": "Best I Ever Had", "status": "Official", "id": "2a781b17-16b9-46f9-adb6-172396f800b9"}]}, {"primary-type": "Single", "artist-credit": [{"artist": {"disambiguation": "Canadian actor/rapper", "name": "Drake", "sort-name": "Drake", "id": "9fff2f8a-21e6-47de-a2b8-7f449929d43f"}}], "ext:score": "100", "id": "6db7f6d4-38c3-4d90-96f7-4e777797b7a4", "title": "Over", "artist-credit-phrase": "Drake", "release-list": [{"title": "Over", "status": "Official", "id": "42f9acbe-aff7-495c-b651-5e7d32ada7c8"}], "type": "Single", "release-count": 1}, {"primary-type": "Single", "artist-credit": [{"artist": {"disambiguation": "Canadian actor/rapper", "name": "Drake", "sort-name": "Drake", "id": "9fff2f8a-21e6-47de-a2b8-7f449929d43f"}}], "ext:score": "100", "id": "ab424192-edf3-42b1-a28b-95755049ba85", "title": "Headlines", "artist-credit-phrase": "Drake", "release-list": [{"title": "Headlines", "status": "Official", "id": "e156b561-a20b-4723-874a-324bacac555b"}], "type": "Single", "release-count": 1}, {"primary-type": "Album", "artist-credit": [{"artist": {"disambiguation": "Canadian actor/rapper", "name": "Drake", "sort-name": "Drake", "id": "9fff2f8a-21e6-47de-a2b8-7f449929d43f"}}], "ext:score": "100", "tag-list": [{"name": "house", "count": "1"}], "id": "eabc69b4-1cd5-4243-9283-7d780722ee2a", "title": "I'm On One", "artist-credit-phrase": "Drake", "release-list": [{"title": "I'm On One", "status": "Promotion", "id": "c8112b05-3a9d-437e-818d-b940dd1d0b0a"}], "secondary-type-list": ["Mixtape/Street"], "type": "Album", "release-count": 1}, {"primary-type": "Single", "artist-credit": [{"artist": {"disambiguation": "Canadian actor/rapper", "name": "Drake", "sort-name": "Drake", "id": "9fff2f8a-21e6-47de-a2b8-7f449929d43f"}}], "ext:score": "100", "id": "f2e4933b-eda2-4226-8253-39341ffc47db", "title": "Find Your Love", "artist-credit-phrase": "Drake", "release-list": [{"title": "Find Your Love", "status": "Official", "id": "46ec1cad-224b-430f-adb7-9ca6b45ac498"}], "type": "Single", "release-count": 1}, {"primary-type": "Single", "artist-credit": [{"artist": {"disambiguation": "Canadian actor/rapper", "name": "Drake", "sort-name": "Drake", "id": "9fff2f8a-21e6-47de-a2b8-7f449929d43f"}}], "ext:score": "100", "id": "0492ab4a-916f-45e3-92ed-1d2cc6052292", "title": "9AM in Dallas", "artist-credit-phrase": "Drake", "release-list": [{"title": "9AM in Dallas", "status": "Official", "id": "f7465811-4c74-4a09-8847-d84cbcf12a15"}], "type": "Single", "release-count": 1}, {"primary-type": "Single", "artist-credit": [{"artist": {"disambiguation": "Electronic DJ", "name": "Drake", "sort-name": "Drake", "id": "7cf5af7a-afa0-4dca-9473-a13508c64e9d"}}], "ext:score": "100", "id": "e234d5eb-9508-4d2a-a555-41ecffef9497", "title": "Banger", "artist-credit-phrase": "Drake", "release-list": [{"title": "Banger", "status": "Official", "id": "55290b67-85ee-4a7e-8ea5-d414f7655cf1"}], "type": "Single", "release-count": 1}, {"primary-type": "Album", "artist-credit": [{"artist": {"disambiguation": "Electronic DJ", "name": "Drake", "sort-name": "Drake", "id": "7cf5af7a-afa0-4dca-9473-a13508c64e9d"}}], "ext:score": "100", "id": "19fe9401-cb75-44e1-acdd-1ca188b373aa", "title": "The Drake LP", "artist-credit-phrase": "Drake", "release-list": [{"title": "The Drake LP", "status": "Official", "id": "4032cbb6-1a01-4ac6-86b0-596e80c490a8"}], "type": "Album", "release-count": 1}, {"primary-type": "Album", "artist-credit": [{"artist": {"disambiguation": "Electronic DJ", "name": "Drake", "sort-name": "Drake", "id": "7cf5af7a-afa0-4dca-9473-a13508c64e9d"}}], "ext:score": "100", "id": "ed3bba5d-2497-4305-bea0-9cc934a86f15", "title": "Dead Perspective", "artist-credit-phrase": "Drake", "release-list": [{"title": "Dead Perspective", "status": "Official", "id": "d727f0fc-4d5f-4d90-8d27-a4ec82a55e4d"}], "type": "Album", "release-count": 1}, {"primary-type": "Single", "artist-credit": [{"artist": {"disambiguation": "Canadian actor/rapper", "name": "Drake", "sort-name": "Drake", "id": "9fff2f8a-21e6-47de-a2b8-7f449929d43f"}}], "ext:score": "100", "tag-list": [{"name": "damm", "count": "1"}], "id": "4509b77b-3058-4a46-84ca-b0c34d2c0d1d", "title": "Marvins Room", "artist-credit-phrase": "Drake", "release-count": 1, "type": "Single", "release-list": [{"title": "Marvins Room", "status": "Official", "id": "aefa18df-aa70-485c-865c-531b44267856"}]}, {"primary-type": "Album", "artist-credit": [{"artist": {"disambiguation": "Canadian actor/rapper", "name": "Drake", "sort-name": "Drake", "id": "9fff2f8a-21e6-47de-a2b8-7f449929d43f"}}], "ext:score": "100", "tag-list": [{"name": "pop", "count": "2"}, {"name": "rap", "count": "2"}, {"name": "hip hop", "count": "2"}, {"name": "pop rap", "count": "3"}, {"name": "pop-rap", "count": "2"}, {"name": "contemporary r&b", "count": "3"}, {"name": "rnb/swing", "count": "3"}], "id": "47809021-4515-4215-beea-db3f5dfb6267", "title": "Take Care", "artist-credit-phrase": "Drake", "release-count": 6, "type": "Album", "release-list": [{"title": "Take Care", "status": "Official", "id": "572bec72-2d3f-4b3e-bf64-580a956a4310"}, {"title": "Take Care", "status": "Official", "id": "02f7e348-b1ae-4c4e-a057-b97f1f56e53c"}, {"title": "Take Care", "status": "Official", "id": "0b4ab5f2-73f0-405f-9add-2330c3a248c1"}, {"title": "Take Care", "status": "Official", "id": "129c3821-2931-4c01-b2c8-9cc96461399d"}, {"title": "Take Care", "status": "Official", "id": "a88b8a9b-7429-485a-8aff-c6900d66596d"}, {"title": "Take Care", "status": "Official", "id": "1e268632-6b5a-4592-bd60-64be3276d104"}]}, {"primary-type": "Album", "artist-credit": [{"artist": {"disambiguation": "Canadian actor/rapper", "name": "Drake", "sort-name": "Drake", "id": "9fff2f8a-21e6-47de-a2b8-7f449929d43f"}}], "ext:score": "100", "tag-list": [{"name": "2014", "count": "1"}, {"name": "year end chart", "count": "1"}, {"name": "billboard hot 100", "count": "1"}], "id": "d56895f6-a276-44bb-938f-921016735fd5", "title": "Nothing Was the Same", "artist-credit-phrase": "Drake", "release-count": 5, "type": "Album", "release-list": [{"title": "Nothing Was The Same", "status": "Official", "id": "e4fe2f16-f07b-4d4e-b86e-151fbd3be4af"}, {"title": "Nothing Was the Same", "status": "Official", "id": "9e7dd586-814e-4ba7-ab18-5b3e554b38a7"}, {"title": "Nothing Was the Same", "status": "Official", "id": "3cbd5631-d95a-493f-9a1e-36de62265871"}, {"title": "Nothing Was the Same", "status": "Official", "id": "cfd78aa4-6938-439e-8be0-e9c51255d35c"}, {"title": "Nothing Was the Same", "status": "Official", "id": "b9b28a72-7cef-4583-8c76-ef2fdd84bd93"}]}, {"primary-type": "Single", "artist-credit": [{"artist": {"disambiguation": "Canadian actor/rapper", "name": "Drake", "sort-name": "Drake", "id": "9fff2f8a-21e6-47de-a2b8-7f449929d43f"}}], "ext:score": "100", "id": "b25918dc-377b-4f31-8caa-bdc21db84437", "title": "5AM in Toronto", "artist-credit-phrase": "Drake", "release-list": [{"title": "5AM in Toronto", "status": "Official", "id": "220fd9e4-f657-439f-b994-d85d9c0b3e5b"}], "type": "Single", "release-count": 1}, {"primary-type": "Album", "artist-credit": [{"artist": {"disambiguation": "Canadian actor/rapper", "name": "Drake", "sort-name": "Drake", "id": "9fff2f8a-21e6-47de-a2b8-7f449929d43f"}}], "ext:score": "100", "tag-list": [{"name": "pop rap", "count": "1"}], "id": "73def4a4-e79f-4a14-9665-b56097a9751f", "title": "Born King", "artist-credit-phrase": "Drake", "release-list": [{"title": "Born King", "status": "Bootleg", "id": "0668e250-1876-4640-bab6-64bace46878d"}], "secondary-type-list": ["Mixtape/Street"], "type": "Album", "release-count": 1}, {"primary-type": "Single", "artist-credit": [{"artist": {"disambiguation": "Canadian actor/rapper", "name": "Drake", "sort-name": "Drake", "id": "9fff2f8a-21e6-47de-a2b8-7f449929d43f"}}], "ext:score": "100", "id": "172deb6a-ce10-4342-bd97-cf6c2e24f965", "title": "OVOXO (TEAMS \u221e TRUST edit)", "artist-credit-phrase": "Drake", "release-list": [{"title": "OVOXO (TEAMS \u221e TRUST edit)", "status": "Bootleg", "id": "d3a4dd27-bdfb-468f-a0d0-c0c5d59cea86"}], "secondary-type-list": ["Remix"], "type": "Single", "release-count": 1}, {"primary-type": "Album", "artist-credit": [{"artist": {"disambiguation": "Canadian actor/rapper", "name": "Drake", "sort-name": "Drake", "id": "9fff2f8a-21e6-47de-a2b8-7f449929d43f"}}], "ext:score": "100", "id": "a5da9d1a-c3dc-4787-a218-622f14981b72", "title": "Thank Us Later: The Remix Album", "artist-credit-phrase": "Drake", "release-list": [{"title": "Thank Us Later: The Remix Album", "status": "Bootleg", "id": "367a36bd-6320-49dc-8a0f-37be376183cf"}], "secondary-type-list": ["Mixtape/Street"], "type": "Album", "release-count": 1}, {"primary-type": "Single", "artist-credit": [{"artist": {"disambiguation": "Canadian actor/rapper", "name": "Drake", "sort-name": "Drake", "id": "9fff2f8a-21e6-47de-a2b8-7f449929d43f"}}], "ext:score": "100", "tag-list": [{"name": "hip-hop", "count": "1"}], "id": "49222baf-b573-48a7-9ea0-8ec6ada313fd", "title": "Trophies", "artist-credit-phrase": "Drake", "release-count": 1, "type": "Single", "release-list": [{"title": "Trophies", "status": "Promotion", "id": "642d1289-a0d2-4d1d-9dca-84dae7a8c340"}]}, {"primary-type": "Single", "artist-credit": [{"artist": {"disambiguation": "Canadian actor/rapper", "name": "Drake", "sort-name": "Drake", "id": "9fff2f8a-21e6-47de-a2b8-7f449929d43f"}}], "ext:score": "100", "id": "06be283d-939a-4fbb-a92d-d3428d4a1b67", "title": "All Me", "artist-credit-phrase": "Drake", "release-list": [{"title": "All Me", "status": "Official", "id": "3e2f8078-1e19-4682-951f-72af2bbd5866"}], "type": "Single", "release-count": 1}]